ide/__init__.py
ide/admin.py
ide/apps.py
ide/decorators.py
ide/models.py
ide/tests.py
ide/urls.py
ide/views.py
ide/static/favicon.ico
ide/static/index.html
ide/static/css/app.39efe745.css
ide/static/css/chunk-08b7e924.a00ffa37.css
ide/static/css/chunk-0ae9009a.7ccac7b3.css
ide/static/css/chunk-0c3d632b.91ac850b.css
ide/static/css/chunk-0ed42f22.6d04e539.css
ide/static/css/chunk-11837a36.0b9dbeff.css
ide/static/css/chunk-24969bde.1e42ded6.css
ide/static/css/chunk-254a1f26.1e42ded6.css
ide/static/css/chunk-28f78c3b.40089a48.css
ide/static/css/chunk-29673d0d.6e3bb214.css
ide/static/css/chunk-2b325361.4798b6d9.css
ide/static/css/chunk-34572102.0b9dbeff.css
ide/static/css/chunk-381fdd14.1e42ded6.css
ide/static/css/chunk-3a433a3c.fcc41532.css
ide/static/css/chunk-3ddea07b.7feb5007.css
ide/static/css/chunk-3fca29e6.d06980e6.css
ide/static/css/chunk-4470fb00.42c093fa.css
ide/static/css/chunk-4c9887e3.b43f01ff.css
ide/static/css/chunk-4d4d2294.1e42ded6.css
ide/static/css/chunk-4da4f04c.69d0732c.css
ide/static/css/chunk-4da8133c.fcc41532.css
ide/static/css/chunk-5260ef46.701f32e3.css
ide/static/css/chunk-53a0991f.40089a48.css
ide/static/css/chunk-542cd929.91ac850b.css
ide/static/css/chunk-5d69bcbd.6d04e539.css
ide/static/css/chunk-647e1549.6e3bb214.css
ide/static/css/chunk-65a5b4c9.cb6d5eca.css
ide/static/css/chunk-67f7b8e5.1e42ded6.css
ide/static/css/chunk-759db5a6.fcc41532.css
ide/static/css/chunk-77e34e3a.4798b6d9.css
ide/static/css/chunk-78f578b7.7feb5007.css
ide/static/css/chunk-7cbc0769.94d8ee91.css
ide/static/css/chunk-81a4c098.94d8ee91.css
ide/static/css/chunk-954b380a.a00ffa37.css
ide/static/css/chunk-a2d197a0.25d54002.css
ide/static/css/chunk-a8fb58ba.f141f328.css
ide/static/css/chunk-b223b738.d06980e6.css
ide/static/css/chunk-b41adfa4.16a404aa.css
ide/static/css/chunk-bce18830.e5ff0d51.css
ide/static/css/chunk-be28f230.7df6edf9.css
ide/static/css/chunk-c1859e86.42c093fa.css
ide/static/css/chunk-c4591bb8.e5ff0d51.css
ide/static/css/chunk-c625a886.f141f328.css
empide_1zlab-0.1.15.dist-info/METADATA
empide_1zlab-0.1.15.dist-info/WHEEL
empide_1zlab-0.1.15.dist-info/top_level.txt
empide_1zlab-0.1.15.dist-info/RECORD
