Metadata-Version: 2.1
Name: empide-1zlab
Version: 0.1.15
Summary: maybe the best develop tools for micropython.
Home-page: http://emp.1zlab.com/
Author: Fuermohao
Author-email: Fuermohao@outlook.com
License: MIT License
Keywords: MicroPython,1ZLAB,EMP,ESP
Platform: Linux
Platform: Unix
Classifier: Environment :: Web Environment
Classifier: Framework :: Django
Classifier: Intended Audience :: Developers
Classifier: License :: OSI Approved :: MIT License
Classifier: Operating System :: OS Independent
Classifier: Programming Language :: Python
Classifier: Programming Language :: Python :: 3
Classifier: Programming Language :: Python :: 3.6
Classifier: Programming Language :: Python :: 3.7
Classifier: Topic :: Internet :: WWW/HTTP
Classifier: Topic :: Internet :: WWW/HTTP :: Dynamic Content
